EukRep/EukRep.py
EukRep/models/linsvm_160_3mer_1.0.pickle
EukRep/models/linsvm_160_3mer_1.1.balanced.pickle
EukRep/models/linsvm_160_3mer_1.1.pickle
EukRep/models/linsvm_160_3mer_1.1.strict.pickle
EukRep/models/linsvm_160_4mer_1.0.pickle
EukRep/models/linsvm_160_4mer_1.1.balanced.pickle
EukRep/models/linsvm_160_4mer_1.1.pickle
EukRep/models/linsvm_160_4mer_1.1.strict.pickle
EukRep/models/linsvm_160_5mer_1.0.pickle
EukRep/models/linsvm_160_5mer_1.1.balanced.pickle
EukRep/models/linsvm_160_5mer_1.1.pickle
EukRep/models/linsvm_160_5mer_1.1.strict.pickle
EukRep/models/linsvm_160_6mer_1.0.pickle
EukRep/models/linsvm_160_6mer_1.1.balanced.pickle
EukRep/models/linsvm_160_6mer_1.1.pickle
EukRep/models/linsvm_160_6mer_1.1.strict.pickle
EukRep/models/linsvm_160_7mer_1.0.pickle
EukRep-0.6.7.data/scripts/EukRep
EukRep-0.6.7.dist-info/LICENSE.txt
EukRep-0.6.7.dist-info/METADATA
EukRep-0.6.7.dist-info/WHEEL
EukRep-0.6.7.dist-info/top_level.txt
EukRep-0.6.7.dist-info/RECORD
