Metadata-Version: 2.1
Name: EukRep
Version: 0.6.7
Summary: Classification of Eukaryotic and Prokaryotic sequences from metagenomic datasets
Home-page: https://github.com/patrickwest/EukRep
Author: Patrick T West
Author-email: patrickwest@berkeley.edu
License: MIT
Platform: UNKNOWN
Requires-Dist: numpy
Requires-Dist: scikit-learn
Requires-Dist: kpal
Requires-Dist: biopython
